AUTHORS.md
CHANGELOG.md
CONTRIBUTING.md
LICENSE
MANIFEST.in
README.md
setup.cfg
setup.py
docs/Makefile
docs/conf.py
docs/make.bat
ebr_connector/__init__.py
ebr_connector.egg-info/PKG-INFO
ebr_connector.egg-info/SOURCES.txt
ebr_connector.egg-info/dependency_links.txt
ebr_connector.egg-info/entry_points.txt
ebr_connector.egg-info/not-zip-safe
ebr_connector.egg-info/requires.txt
ebr_connector.egg-info/top_level.txt
ebr_connector/examples/__init__.py
ebr_connector/examples/query.py
ebr_connector/hooks/__init__.py
ebr_connector/hooks/common/__init__.py
ebr_connector/hooks/common/args.py
ebr_connector/hooks/common/store_results.py
ebr_connector/hooks/jenkins/__init__.py
ebr_connector/hooks/jenkins/store_results.py
ebr_connector/index/__init__.py
ebr_connector/index/generate_template.py
ebr_connector/prepacked_queries/__init__.py
ebr_connector/prepacked_queries/multi_jobs.py
ebr_connector/prepacked_queries/query.py
ebr_connector/prepacked_queries/single_jobs.py
ebr_connector/schema/__init__.py
ebr_connector/schema/build_results.py
ebr_connector/schema/dynamic_template.py
tests/__init__.py
tests/integration/__init__.py
tests/integration/examples/__init__.py
tests/integration/examples/conftest.py
tests/integration/examples/test_query.py
tests/unit/__init__.py
tests/unit/hooks/__init__.py
tests/unit/hooks/jenkins/__init__.py
tests/unit/hooks/jenkins/test_store_results.py
tests/unit/schema/__init__.py
tests/unit/schema/test_build_results_document.py
tests/unit/schema/test_test_innerdoc.py
tests/unit/schema/test_test_summary_innerdoc.py
tests/unit/schema/test_tests_innerdoc.py
tests/unit/schema/test_testsuite_innerdoc.py