Metadata-Version: 2.1
Name: ebr-connector
Version: 0.1.1
Summary: Simple Python package to define a schema for build and test results to be stored in Elasticsearch.
Home-page: https://github.com/tomtom-international/ebr-connector
Author: Eugene Davis
Author-email: eugene.davis@tomtom.com
License: Apache License 2.0
Keywords: ebr_connector
Platform: UNKNOWN
Classifier: Intended Audience :: Developers
Classifier: License :: OSI Approved :: Apache Software License
Classifier: Natural Language :: English
Classifier: Programming Language :: Python :: 3
Classifier: Programming Language :: Python :: 3.5
Classifier: Programming Language :: Python :: 3.6
Classifier: Programming Language :: Python :: 3.7
